bellhop/__init__.py
bellhop/errors.py
bellhop/model.py
bellhop_parse-0.2.0.dist-info/WHEEL
bellhop_parse-0.2.0.dist-info/METADATA
bellhop_parse-0.2.0.dist-info/RECORD
