Metadata-Version: 2.3
Name: bellhop-parse
Version: 0.2.0
Summary: Binary deserialization
Keywords: parsing,deserialization
Author: Daniel Walker
Author-email: Daniel Walker <nickeldan@gmail.com>
License: MIT License
Classifier: Topic :: Software Development :: Libraries
Classifier: License :: OSI Approved :: MIT License
Classifier: Programming Language :: Python :: 3
Classifier: Programming Language :: Python :: 3.10
Classifier: Typing :: Typed
Classifier: Natural Language :: English
Requires-Python: >=3.10.0
Project-URL: Repository, https://gitlab.com/nickeldan/bellhop
